[
  {
    "author": "Ed Sheeran",
    "quote": "Success is the best revenge for anything."
  },
  {
    "author": "Winnie The Pooh",
    "quote": "A day without a friend is like a pot without a single drop of honey left inside."
  },
  {
    "author": "Walt Disney",
    "quote": "The way to get started is to quit talking and begin doing."
  },
  {
    "author": "Tom Hanks",
    "quote": "If it wasn't hard, everyone would do it. It's the hard that makes it great."
  },
  {
    "author": "Denzel Washington",
    "quote": "You pray for rain, you gotta deal with the mud too. That's a part of it."
  },
  {
    "author": "Socrates",
    "quote": "Be slow to fall into friendship, but when thou art in, continue firm and constant."
  },
  {
    "author": "Leonardo Da Vinci",
    "quote": "Simplicity is the ultimate sophistication."
  },
  {
    "author": "Sherlock Holmes",
    "quote": "To a great mind, nothing is little."
  },
  {
    "author": "Mahatma Gandhi",
    "quote": "You must be the change you wish to see in the world."
  },
  {
    "author": "Steve Jobs",
    "quote": "Stay hungry. Stay foolish."
  },
  {
    "author": "Lady And The Tramp",
    "quote": "There's a great big hunk of world down there with no fence around it."
  },
  {
    "author": "Winnie The Pooh",
    "quote": "Life is a journey to be experienced, not a problem to be solved."
  }
]